sonarqube_api/__init__.py
sonarqube_api/api.py
sonarqube_api/exceptions.py
sonarqube_api/utils.py
sonarqube_api/cmd/__init__.py
sonarqube_api/cmd/activate_rules.py
sonarqube_api/cmd/export_rules.py
sonarqube_api/cmd/migrate_rules.py
sonarqube_api-1.3.1.dist-info/DESCRIPTION.rst
sonarqube_api-1.3.1.dist-info/METADATA
sonarqube_api-1.3.1.dist-info/RECORD
sonarqube_api-1.3.1.dist-info/WHEEL
sonarqube_api-1.3.1.dist-info/entry_points.txt
sonarqube_api-1.3.1.dist-info/metadata.json
sonarqube_api-1.3.1.dist-info/top_level.txt
