Metadata-Version: 2.0
Name: sonarqube-api
Version: 1.3.1
Summary: SonarQube API Handler
Home-page: https://github.com/kako-nawao/python-sonarqube-api
Author: Claudio Omar Melendrez Baeza
Author-email: claudio.melendrez@gmail.com
License: MIT
Keywords: api sonar sonarqube
Platform: UNKNOWN
Classifier: Development Status :: 5 - Production/Stable
Classifier: Environment :: Plugins
Classifier: Intended Audience :: Developers
Classifier: License :: OSI Approved :: MIT License
Classifier: Operating System :: OS Independent
Classifier: Programming Language :: Python :: 2.7
Classifier: Programming Language :: Python :: 3.4
Classifier: Programming Language :: Python :: 3.5
Classifier: Programming Language :: Python :: 3.6
Classifier: Topic :: Software Development
Requires-Dist: requests (<2.99,>=2.9)
